{"variables":[],"info":{"name":"","_postman_id":"dbcb4e71-1fc2-4fb2-a1bc-7630b3c247bd","description":"","schema":"https:\/\/schema.getpostman.com\/json\/collection\/v2.0.0\/collection.json"},"item":[{"name":"AgencyController","description":"","item":[{"name":"index","request":{"url":"http:\/\/localhost\/api\/agencies","method":"GET","body":{"mode":"formdata","formdata":[]},"description":"Display a listing of the agencies.","response":[]}},{"name":"Display the specified agency.","request":{"url":"http:\/\/localhost\/api\/agencies\/{id}","method":"GET","body":{"mode":"formdata","formdata":[]},"description":"","response":[]}},{"name":"Update the specified agency in storage.","request":{"url":"http:\/\/localhost\/api\/agencies\/{id}","method":"PUT","body":{"mode":"formdata","formdata":[]},"description":"","response":[]}}]},{"name":"general","description":"","item":[{"name":"http:\/\/localhost\/api\/auth\/agency\/signup","request":{"url":"http:\/\/localhost\/api\/auth\/agency\/signup","method":"POST","body":{"mode":"formdata","formdata":[{"key":"name","value":"ut","type":"text","enabled":true},{"key":"email","value":"wendell.gusikowski@example.net","type":"text","enabled":true},{"key":"password","value":"ut","type":"text","enabled":true},{"key":"agency","value":"ut","type":"text","enabled":true}]},"description":"","response":[]}},{"name":"http:\/\/localhost\/api\/auth\/signup","request":{"url":"http:\/\/localhost\/api\/auth\/signup","method":"POST","body":{"mode":"formdata","formdata":[{"key":"name","value":"in","type":"text","enabled":true},{"key":"email","value":"anissa63@example.com","type":"text","enabled":true},{"key":"password","value":"in","type":"text","enabled":true},{"key":"agency_id","value":9,"type":"text","enabled":true},{"key":"customer_id","value":9,"type":"text","enabled":true}]},"description":"","response":[]}},{"name":"http:\/\/localhost\/api\/auth\/login","request":{"url":"http:\/\/localhost\/api\/auth\/login","method":"POST","body":{"mode":"formdata","formdata":[{"key":"email","value":"runolfsson.werner@example.com","type":"text","enabled":true},{"key":"password","value":"corrupti","type":"text","enabled":true}]},"description":"","response":[]}},{"name":"http:\/\/localhost\/api\/auth\/recovery","request":{"url":"http:\/\/localhost\/api\/auth\/recovery","method":"POST","body":{"mode":"formdata","formdata":[{"key":"email","value":"delfina.blanda@example.net","type":"text","enabled":true}]},"description":"","response":[]}},{"name":"http:\/\/localhost\/api\/auth\/reset","request":{"url":"http:\/\/localhost\/api\/auth\/reset","method":"POST","body":{"mode":"formdata","formdata":[{"key":"token","value":"quia","type":"text","enabled":true},{"key":"email","value":"richie.christiansen@example.net","type":"text","enabled":true},{"key":"password","value":"quia","type":"text","enabled":true}]},"description":"","response":[]}},{"name":"Display a listing of the resource.","request":{"url":"http:\/\/localhost\/api\/templates","method":"GET","body":{"mode":"formdata","formdata":[]},"description":"","response":[]}},{"name":"Store a newly created resource in storage.","request":{"url":"http:\/\/localhost\/api\/templates","method":"POST","body":{"mode":"formdata","formdata":[]},"description":"","response":[]}},{"name":"Display the specified resource.","request":{"url":"http:\/\/localhost\/api\/templates\/{template}","method":"GET","body":{"mode":"formdata","formdata":[]},"description":"","response":[]}},{"name":"Update the specified resource in storage.","request":{"url":"http:\/\/localhost\/api\/templates\/{template}","method":"PUT","body":{"mode":"formdata","formdata":[]},"description":"","response":[]}},{"name":"Remove the specified resource from storage.","request":{"url":"http:\/\/localhost\/api\/templates\/{template}","method":"DELETE","body":{"mode":"formdata","formdata":[]},"description":"","response":[]}},{"name":"Display a listing of the resource.","request":{"url":"http:\/\/localhost\/api\/templates\/{template_id}\/steps","method":"GET","body":{"mode":"formdata","formdata":[]},"description":"","response":[]}},{"name":"Store a newly created resource in storage.","request":{"url":"http:\/\/localhost\/api\/templates\/{template_id}\/steps","method":"POST","body":{"mode":"formdata","formdata":[]},"description":"","response":[]}},{"name":"Display the specified resource.","request":{"url":"http:\/\/localhost\/api\/templates\/{template_id}\/steps\/{step}","method":"GET","body":{"mode":"formdata","formdata":[]},"description":"","response":[]}},{"name":"Update the specified resource in storage.","request":{"url":"http:\/\/localhost\/api\/templates\/{template_id}\/steps\/{step}","method":"PUT","body":{"mode":"formdata","formdata":[]},"description":"","response":[]}},{"name":"Remove the specified resource from storage.","request":{"url":"http:\/\/localhost\/api\/templates\/{template_id}\/steps\/{step}","method":"DELETE","body":{"mode":"formdata","formdata":[]},"description":"","response":[]}},{"name":"Display a listing of the resource.","request":{"url":"http:\/\/localhost\/api\/templates\/{template_id}\/steps\/{step_id}\/details","method":"GET","body":{"mode":"formdata","formdata":[]},"description":"","response":[]}},{"name":"Store a newly created resource in storage.","request":{"url":"http:\/\/localhost\/api\/templates\/{template_id}\/steps\/{step_id}\/details","method":"POST","body":{"mode":"formdata","formdata":[]},"description":"","response":[]}},{"name":"Display the specified resource.","request":{"url":"http:\/\/localhost\/api\/templates\/{template_id}\/steps\/{step_id}\/details\/{detail}","method":"GET","body":{"mode":"formdata","formdata":[]},"description":"","response":[]}},{"name":"Update the specified resource in storage.","request":{"url":"http:\/\/localhost\/api\/templates\/{template_id}\/steps\/{step_id}\/details\/{detail}","method":"PUT","body":{"mode":"formdata","formdata":[]},"description":"","response":[]}},{"name":"Remove the specified resource from storage.","request":{"url":"http:\/\/localhost\/api\/templates\/{template_id}\/steps\/{step_id}\/details\/{detail}","method":"DELETE","body":{"mode":"formdata","formdata":[]},"description":"","response":[]}},{"name":"http:\/\/localhost\/api\/subscriber","request":{"url":"http:\/\/localhost\/api\/subscriber","method":"GET","body":{"mode":"formdata","formdata":[]},"description":"","response":[]}},{"name":"http:\/\/localhost\/api\/{user_id}\/confirm","request":{"url":"http:\/\/localhost\/api\/{user_id}\/confirm","method":"POST","body":{"mode":"formdata","formdata":[]},"description":"","response":[]}},{"name":"http:\/\/localhost\/api\/{user_id}\/subscription","request":{"url":"http:\/\/localhost\/api\/{user_id}\/subscription","method":"POST","body":{"mode":"formdata","formdata":[]},"description":"","response":[]}},{"name":"http:\/\/localhost\/api\/users","request":{"url":"http:\/\/localhost\/api\/users","method":"GET","body":{"mode":"formdata","formdata":[]},"description":"","response":[]}},{"name":"http:\/\/localhost\/api\/users","request":{"url":"http:\/\/localhost\/api\/users","method":"POST","body":{"mode":"formdata","formdata":[]},"description":"","response":[]}},{"name":"http:\/\/localhost\/api\/users\/{user_id}","request":{"url":"http:\/\/localhost\/api\/users\/{user_id}","method":"PUT","body":{"mode":"formdata","formdata":[]},"description":"","response":[]}},{"name":"http:\/\/localhost\/api\/users\/{user_id}","request":{"url":"http:\/\/localhost\/api\/users\/{user_id}","method":"DELETE","body":{"mode":"formdata","formdata":[]},"description":"","response":[]}},{"name":"Display a listing of the resource.","request":{"url":"http:\/\/localhost\/api\/customers","method":"GET","body":{"mode":"formdata","formdata":[]},"description":"","response":[]}},{"name":"Store a newly created resource in storage.","request":{"url":"http:\/\/localhost\/api\/customers","method":"POST","body":{"mode":"formdata","formdata":[]},"description":"","response":[]}},{"name":"Update the specified resource in storage.","request":{"url":"http:\/\/localhost\/api\/customers\/{customer_id}","method":"PUT","body":{"mode":"formdata","formdata":[]},"description":"","response":[]}},{"name":"Remove the specified resource from storage.","request":{"url":"http:\/\/localhost\/api\/customers\/{customer_id}","method":"DELETE","body":{"mode":"formdata","formdata":[]},"description":"","response":[]}},{"name":"Display a listing of the resource.","request":{"url":"http:\/\/localhost\/api\/customers\/{customer_id}\/projects","method":"GET","body":{"mode":"formdata","formdata":[]},"description":"","response":[]}},{"name":"Store a newly created resource in storage.","request":{"url":"http:\/\/localhost\/api\/customers\/{customer_id}\/projects","method":"POST","body":{"mode":"formdata","formdata":[]},"description":"","response":[]}},{"name":"Update the specified resource in storage.","request":{"url":"http:\/\/localhost\/api\/customers\/{customer_id}\/projects\/{project_id}","method":"PUT","body":{"mode":"formdata","formdata":[]},"description":"","response":[]}},{"name":"Remove the specified resource from storage.","request":{"url":"http:\/\/localhost\/api\/customers\/{customer_id}\/projects\/{project_id}","method":"DELETE","body":{"mode":"formdata","formdata":[]},"description":"","response":[]}},{"name":"Display a listing of the resource.","request":{"url":"http:\/\/localhost\/api\/customers\/{customer_id}\/projects\/{project_id}\/tasks","method":"GET","body":{"mode":"formdata","formdata":[]},"description":"","response":[]}},{"name":"Store a newly created resource in storage.","request":{"url":"http:\/\/localhost\/api\/customers\/{customer_id}\/projects\/{project_id}\/tasks","method":"POST","body":{"mode":"formdata","formdata":[]},"description":"","response":[]}},{"name":"TODO: implementare modifica template","request":{"url":"http:\/\/localhost\/api\/customers\/{customer_id}\/projects\/{project_id}\/tasks\/{task_id}","method":"PUT","body":{"mode":"formdata","formdata":[]},"description":"","response":[]}},{"name":"Remove the specified resource from storage.","request":{"url":"http:\/\/localhost\/api\/customers\/{customer_id}\/projects\/{project_id}\/tasks\/{task_id}","method":"DELETE","body":{"mode":"formdata","formdata":[]},"description":"","response":[]}},{"name":"http:\/\/localhost\/api\/customers\/{customer_id}\/projects\/{project_id}\/tasks\/{task_id}\/details\/{detail_step_task_id}\/files","request":{"url":"http:\/\/localhost\/api\/customers\/{customer_id}\/projects\/{project_id}\/tasks\/{task_id}\/details\/{detail_step_task_id}\/files","method":"POST","body":{"mode":"formdata","formdata":[]},"description":"","response":[]}},{"name":"http:\/\/localhost\/api\/customers\/{customer_id}\/projects\/{project_id}\/tasks\/{task_id}\/details\/{detail_step_task_id}\/files\/{file_id}\/download","request":{"url":"http:\/\/localhost\/api\/customers\/{customer_id}\/projects\/{project_id}\/tasks\/{task_id}\/details\/{detail_step_task_id}\/files\/{file_id}\/download","method":"GET","body":{"mode":"formdata","formdata":[]},"description":"","response":[]}},{"name":"http:\/\/localhost\/api\/customers\/{customer_id}\/projects\/{project_id}\/tasks\/{task_id}\/details\/{detail_step_task_id}\/files\/{file_id}","request":{"url":"http:\/\/localhost\/api\/customers\/{customer_id}\/projects\/{project_id}\/tasks\/{task_id}\/details\/{detail_step_task_id}\/files\/{file_id}","method":"DELETE","body":{"mode":"formdata","formdata":[]},"description":"","response":[]}},{"name":"http:\/\/localhost\/api\/customers\/{customer_id}\/projects\/{project_id}\/tasks\/{task_id}\/details\/{detail_step_task_id}\/files","request":{"url":"http:\/\/localhost\/api\/customers\/{customer_id}\/projects\/{project_id}\/tasks\/{task_id}\/details\/{detail_step_task_id}\/files","method":"GET","body":{"mode":"formdata","formdata":[]},"description":"","response":[]}},{"name":"http:\/\/localhost\/api\/customers\/{customer_id}\/projects\/{project_id}\/tasks\/{task_id}\/details\/{detail_step_task_id}\/files\/{file_id}\/approve","request":{"url":"http:\/\/localhost\/api\/customers\/{customer_id}\/projects\/{project_id}\/tasks\/{task_id}\/details\/{detail_step_task_id}\/files\/{file_id}\/approve","method":"POST","body":{"mode":"formdata","formdata":[]},"description":"","response":[]}},{"name":"http:\/\/localhost\/api\/customers\/{customer_id}\/projects\/{project_id}\/tasks\/{task_id}\/details\/{detail_step_task_id}\/files\/{file_id}\/disapprove","request":{"url":"http:\/\/localhost\/api\/customers\/{customer_id}\/projects\/{project_id}\/tasks\/{task_id}\/details\/{detail_step_task_id}\/files\/{file_id}\/disapprove","method":"POST","body":{"mode":"formdata","formdata":[]},"description":"","response":[]}},{"name":"http:\/\/localhost\/api\/customers\/{customer_id}\/projects\/{project_id}\/tasks\/{task_id}\/details\/{detail_step_task_id}\/dates","request":{"url":"http:\/\/localhost\/api\/customers\/{customer_id}\/projects\/{project_id}\/tasks\/{task_id}\/details\/{detail_step_task_id}\/dates","method":"POST","body":{"mode":"formdata","formdata":[]},"description":"","response":[]}},{"name":"http:\/\/localhost\/api\/customers\/{customer_id}\/projects\/{project_id}\/tasks\/{task_id}\/details\/{detail_step_task_id}\/dates","request":{"url":"http:\/\/localhost\/api\/customers\/{customer_id}\/projects\/{project_id}\/tasks\/{task_id}\/details\/{detail_step_task_id}\/dates","method":"GET","body":{"mode":"formdata","formdata":[]},"description":"","response":[]}},{"name":"http:\/\/localhost\/api\/customers\/{customer_id}\/projects\/{project_id}\/tasks\/{task_id}\/details\/{detail_step_task_id}\/dates\/{date_id}\/approve","request":{"url":"http:\/\/localhost\/api\/customers\/{customer_id}\/projects\/{project_id}\/tasks\/{task_id}\/details\/{detail_step_task_id}\/dates\/{date_id}\/approve","method":"POST","body":{"mode":"formdata","formdata":[]},"description":"","response":[]}},{"name":"http:\/\/localhost\/api\/customers\/{customer_id}\/projects\/{project_id}\/tasks\/{task_id}\/details\/{detail_step_task_id}\/dates\/{date_id}\/disapprove","request":{"url":"http:\/\/localhost\/api\/customers\/{customer_id}\/projects\/{project_id}\/tasks\/{task_id}\/details\/{detail_step_task_id}\/dates\/{date_id}\/disapprove","method":"POST","body":{"mode":"formdata","formdata":[]},"description":"","response":[]}},{"name":"http:\/\/localhost\/api\/customers\/{customer_id}\/projects\/{project_id}\/tasks\/{task_id}\/details\/{detail_step_task_id}\/dates\/{date_id}","request":{"url":"http:\/\/localhost\/api\/customers\/{customer_id}\/projects\/{project_id}\/tasks\/{task_id}\/details\/{detail_step_task_id}\/dates\/{date_id}","method":"DELETE","body":{"mode":"formdata","formdata":[]},"description":"","response":[]}}]}]}